[
  {
    "unbind": {
      "ctrl-q": "zed::Quit",
      "ctrl-shift-w": "workspace::CloseWindow"
    },
    "bindings": {
      // Toggles via Hyper key (super+ctrl+alt+shift)
      // "super-ctrl-alt-shift-enter": "agent::ToggleFocus", // use enter, space+a is used for code actions
      // "super-ctrl-alt-shift-d": "debug_panel::ToggleFocus",
      // "super-ctrl-alt-shift-e": "project_panel::ToggleFocus",
      // "super-ctrl-alt-shift-g": "git_panel::ToggleFocus",
      // "super-ctrl-alt-shift-o": "outline_panel::ToggleFocus",
      // "super-ctrl-alt-shift-t": "terminal_panel::ToggleFocus"
    }
  },
  {
    "context": "Workspace",
    "unbind": {
      "ctrl-alt-s": "workspace::SaveAll",
      "ctrl-shift-d": "debug_panel::ToggleFocus",
      "ctrl-t": "project_symbols::Toggle"
    },
    "bindings": {
      "ctrl-~": "workspace::NewCenterTerminal", // default: workspace::NewTerminal

      // Toggles via Meh key (ctrl+alt+shift)
      "ctrl-alt-(": "workspace::ToggleLeftDock",
      "ctrl-alt-)": "workspace::ToggleRightDock"
    }
  },
  {
    "context": "Terminal",
    "unbind": {
      "ctrl-shift-w": "pane::CloseActiveItem"
    },
    "bindings": {
      "ctrl-alt-w": "pane::CloseActiveItem"
    }
  },
  {
    "context": "!Terminal",
    "unbind": {
      // Disable because I keep hitting this key combo accidentally.
      "ctrl-shift-c": "collab_panel::ToggleFocus"
    }
  },
  {
    // Needed for which_key popup to stay open.
    "context": "VimControl && !menu",
    "unbind": {
      "space": "vim::WrappingRight"
    }
  },
  {
    "context": "(vim_mode == helix_normal || vim_mode == helix_select) && !menu",
    "unbind": {
      "ctrl-s": "editor::SaveLocation"
    },
    "bindings": {
      "ctrl-alt-s": "editor::SaveLocation",
      "ctrl-alt-w": "pane::CloseActiveItem",
      "ctrl-q": "pane::CloseActiveItem",

      // Line Selection (Aligns with Helix x/X)
      "shift-x": "editor::SelectUp",

      // Splits/Pane Navigation (Aligns with Helix C-h/j/k/l)
      "ctrl-h": "workspace::ActivatePaneLeft",
      "ctrl-j": "workspace::ActivatePaneDown",
      "ctrl-k": "workspace::ActivatePaneUp",
      "ctrl-l": "workspace::ActivatePaneRight",

      // AST Parent Node Navigation (Aligns with Helix tab/S-tab)
      "tab": "editor::SelectLargerSyntaxNode",
      "shift-tab": "editor::SelectSmallerSyntaxNode",

      // space.l minor mode formatting & toggles
      "space l f": "editor::Format",
      "space l q": "editor::Rewrap",
      "space l s": "editor::SortLinesCaseInsensitive",
      "space l i": "editor::ToggleInlayHints",
      "space l z": "editor::ToggleSoftWrap"
    }
  }
]
